LICENSE
README.rst
setup.cfg
setup.py
examples/__init__.py
examples/basic_scheduler.py
examples/rabbitmq_scheduler.py
examples/service_scheduler.py
storm.scheduler.egg-info/PKG-INFO
storm.scheduler.egg-info/SOURCES.txt
storm.scheduler.egg-info/dependency_links.txt
storm.scheduler.egg-info/top_level.txt
storm_scheduler/__init__.py
storm_scheduler/base.py
storm_scheduler/exception.py
storm_scheduler/scheduler.py
storm_scheduler/task.py
storm_scheduler/tests/__init__.py
storm_scheduler/tests/test_scheduler.py